hello_verysimplemodule/__init__.py
hello_verysimplemodule/add.py
hello_verysimplemodule/subtract.py
hello_verysimplemodule/extras/__init__.py
hello_verysimplemodule/extras/divide.py
hello_verysimplemodule/extras/multiply.py
hello_verysimplemodule-0.0.1.dist-info/METADATA
hello_verysimplemodule-0.0.1.dist-info/WHEEL
hello_verysimplemodule-0.0.1.dist-info/top_level.txt
hello_verysimplemodule-0.0.1.dist-info/RECORD
